LICENSE
MANIFEST.in
README.md
setup.py
libpythonpro_ravellys/__init__.py
libpythonpro_ravellys/github_api.py
libpythonpro_ravellys.egg-info/PKG-INFO
libpythonpro_ravellys.egg-info/SOURCES.txt
libpythonpro_ravellys.egg-info/dependency_links.txt
libpythonpro_ravellys.egg-info/not-zip-safe
libpythonpro_ravellys.egg-info/requires.txt
libpythonpro_ravellys.egg-info/top_level.txt